scpeft/__init__.py
scpeft/data_collator.py
scpeft/data_sampler.py
scpeft/loss.py
scpeft/model/MultiheadAttentionLoRA.py
scpeft/model/__init__.py
scpeft/model/dsbn.py
scpeft/model/generation_model.py
scpeft/model/grad_reverse.py
scpeft/model/model.py
scpeft/model/multiomic_model.py
scpeft/preprocess.py
scpeft/tasks/__init__.py
scpeft/tasks/cell_emb.py
scpeft/tasks/grn.py
scpeft/tokenizer/__init__.py
scpeft/tokenizer/default_census_vocab.json
scpeft/tokenizer/default_gene_vocab.json
scpeft/tokenizer/gene_tokenizer.py
scpeft/trainer.py
scpeft/utils/__init__.py
scpeft/utils/util.py
scpeft-0.1.2.dist-info/LICENSE
scpeft-0.1.2.dist-info/METADATA
scpeft-0.1.2.dist-info/WHEEL
scpeft-0.1.2.dist-info/RECORD
